localcurl/__init__.py
localcurl/cli.py
localcurl/parsers.py
localcurl/request_adapters.py
localcurl-0.4.0.dist-info/METADATA
localcurl-0.4.0.dist-info/WHEEL
localcurl-0.4.0.dist-info/entry_points.txt
localcurl-0.4.0.dist-info/licenses/LICENSE
localcurl-0.4.0.dist-info/RECORD
