Metadata-Version: 2.4
Name: localcurl
Version: 0.4.0
Summary: Replay remote curl requests locally
Author: Sylvain Gable
License-Expression: MIT
License-File: LICENSE
Requires-Python: >=3.9
Requires-Dist: pyperclip>=1.9.0
Requires-Dist: requests>=2.32.3
Requires-Dist: typer>=0.12.0
